memchain/__init__.py
memchain/modules.py
memchain/prompts.py
memchain-0.0.1.dist-info/METADATA
memchain-0.0.1.dist-info/WHEEL
memchain-0.0.1.dist-info/top_level.txt
memchain-0.0.1.dist-info/RECORD
