Metadata-Version: 2.1
Name: memchain
Version: 0.0.1
Summary: Memchain helps llms respond using Memgraph as the knowledge base.
Author: Ahsan Nayaz
Author-email: ahsannayaz@outlook.com
Keywords: python,first package
Classifier: Development Status :: 3 - Alpha
Classifier: Intended Audience :: Education
Classifier: Programming Language :: Python :: 2
Classifier: Programming Language :: Python :: 3
Classifier: Operating System :: MacOS :: MacOS X
Classifier: Operating System :: Microsoft :: Windows
Requires-Dist: gqlalchemy
Requires-Dist: openai
